{
  "project_info": {
    "project_number": "135420437320",
    "project_id": "pizza-shop-170e0",
    "storage_bucket": "pizza-shop-170e0.firebasestorage.app"
  },
  "client": [
    {
      "client_info": {
        "mobilesdk_app_id": "1:135420437320:android:ac154852a4fbfc4bd4497d",
        "android_client_info": {
          "package_name": "com.example.pizza"
        }
      },
      "oauth_client": [],
      "api_key": [
        {
          "current_key": "AIzaSyAQ_3R_M2Uo6-331a05-EQN18-n06GoNUY"
        }
      ],
      "services": {
        "appinvite_service": {
          "other_platform_oauth_client": []
        }
      }
    }
  ],
  "configuration_version": "1"
}